Metadata-Version: 2.1
Name: django-configurations-google-analytics
Version: 2020.7.1
Summary: django-configurations Google Analytics settings
Home-page: https://github.com/andrewp-as-is/django-configurations-google-analytics.py
License: Unlicense
Keywords: django google analytics
Platform: UNKNOWN
Classifier: Framework :: Django
Classifier: License :: Public Domain
Classifier: Operating System :: OS Independent
Classifier: Programming Language :: Python :: 3
